majadigi/__init__.py
majadigi/cleansing_data.py
majadigi-0.1.9.dist-info/METADATA
majadigi-0.1.9.dist-info/WHEEL
majadigi-0.1.9.dist-info/top_level.txt
majadigi-0.1.9.dist-info/RECORD
