Metadata-Version: 2.4
Name: majadigi
Version: 0.1.9
Summary: Library untuk cleansing dan transformasi data wilayah Jatim
Home-page: https://github.com/UWWAWWU/Library-Majadigi
Author: Wawu Tri Ambodo
Author-email: wawutri1706@gmail.com
Classifier: Programming Language :: Python :: 3
Classifier: Operating System :: OS Independent
Requires-Python: >=3.8
Requires-Dist: pandas
Requires-Dist: psycopg2-binary
Requires-Dist: sqlalchemy
Requires-Dist: tabulate
Requires-Dist: scikit-learn
Dynamic: author
Dynamic: author-email
Dynamic: classifier
Dynamic: description
Dynamic: description-content-type
Dynamic: home-page
Dynamic: requires-dist
Dynamic: requires-python
Dynamic: summary
